README.txt
setup.py
docs/HISTORY.txt
docs/INSTALL.txt
docs/LICENSE.GPL
docs/LICENSE.txt
mfabrik/__init__.py
mfabrik.behaviorutilities.egg-info/PKG-INFO
mfabrik.behaviorutilities.egg-info/SOURCES.txt
mfabrik.behaviorutilities.egg-info/dependency_links.txt
mfabrik.behaviorutilities.egg-info/entry_points.txt
mfabrik.behaviorutilities.egg-info/namespace_packages.txt
mfabrik.behaviorutilities.egg-info/not-zip-safe
mfabrik.behaviorutilities.egg-info/paster_plugins.txt
mfabrik.behaviorutilities.egg-info/requires.txt
mfabrik.behaviorutilities.egg-info/top_level.txt
mfabrik/behaviorutilities/__init__.py
mfabrik/behaviorutilities/assignable.py
mfabrik/behaviorutilities/configure.zcml
mfabrik/behaviorutilities/debug.py
mfabrik/behaviorutilities/tests.py
mfabrik/behaviorutilities/traverse.py
mfabrik/behaviorutilities/views.py
mfabrik/behaviorutilities/viewutils.py
mfabrik/behaviorutilities/volatilecontext.py
mfabrik/behaviorutilities/templates/z3cformview.pt