Metadata-Version: 1.0
Name: mfabrik.behaviorutilities
Version: 0.1
Summary: Helper patterns to create behaviors for Archetypes content with plone.behavior package
Home-page: http://svn.plone.org/svn/collective/
Author: mFabrik Research Oy
Author-email: info@mfabrik.com
License: GPL
Keywords: plone behavior archetypes
Platform: UNKNOWN
Classifier: Framework :: Plone
Classifier: Programming Language :: Python
